{
    "name": "IR4",
    "students": [
        {
            "GUID": "e140e1d2-7b3c-4c8c-a89f-8564912e4a11",
            "gender": "female",
            "firstname": "Jessamine",
            "lastname": "Tremblay",
            "streetaddress": "3 avenue de Bouvines",
            "city": "SCHOELCHER",
            "zipcode": "97233",
            "country": "France",
            "birthdate": "8/2/1996",
            "picture": null
        },
        {
            "GUID": "2c6296ac-d329-415d-9d54-464c9d11aad0",
            "gender": "male",
            "firstname": "J\u00e9r\u00f4me",
            "lastname": "Arnoux",
            "streetaddress": "57 avenue du Marechal Juin",
            "city": "SAINT-LEU",
            "zipcode": "97436",
            "country": "France",
            "birthdate": "6/13/2000",
            "picture": null
        },
        {
            "GUID": "f6e9a83f-32e6-43ec-9dc8-b616e04d5d22",
            "gender": "female",
            "firstname": "Solaine",
            "lastname": "Faure",
            "streetaddress": "12 Chemin Challet",
            "city": "LILLE",
            "zipcode": "59800",
            "country": "France",
            "birthdate": "1/18/1999",
            "picture": null
        },
        {
            "GUID": "5aed43c9-76ad-4f70-b883-d2f26d9dd8f0",
            "gender": "female",
            "firstname": "\u00c9lise",
            "lastname": "Huot",
            "streetaddress": "79 rue des Dunes",
            "city": "SAINT-MAUR-DES-FOSS\u00c8S",
            "zipcode": "94100",
            "country": "France",
            "birthdate": "4/30/1998",
            "picture": null
        },
        {
            "GUID": "6c2c8386-85a1-42a6-80ee-60e6ed9eed69",
            "gender": "female",
            "firstname": "Azura",
            "lastname": "Gagn\u00e9",
            "streetaddress": "88 Quai des Belges",
            "city": "MEAUX",
            "zipcode": "77100",
            "country": "France",
            "birthdate": "10/25/1996",
            "picture": null
        },
        {
            "GUID": "2e3e71c4-ef97-4632-8d06-9b2958eda41e",
            "gender": "female",
            "firstname": "Constance",
            "lastname": "Barteaux",
            "streetaddress": "74 Chemin Du Lavarin Sud",
            "city": "CAHORS",
            "zipcode": "46000",
            "country": "France",
            "birthdate": "8/15/1997",
            "picture": null
        },
        {
            "GUID": "ee951db4-2e53-45e4-be4f-3eb8371acfce",
            "gender": "female",
            "firstname": "Durandana",
            "lastname": "Goguen",
            "streetaddress": "83 Rue Joseph Vernet",
            "city": "BAR-LE-DUC",
            "zipcode": "55000",
            "country": "France",
            "birthdate": "12/11/1998",
            "picture": null
        },
        {
            "GUID": "fc06e391-1d4c-4ce1-84b4-6eb38156d169",
            "gender": "female",
            "firstname": "Sylvie",
            "lastname": "Simon",
            "streetaddress": "62 rue Charles Corbeau",
            "city": "FLEURY-LES-AUBRAIS",
            "zipcode": "45400",
            "country": "France",
            "birthdate": "6/10/1997",
            "picture": null
        },
        {
            "GUID": "cb073e5c-ac00-41bc-8f28-845baa75e57c",
            "gender": "female",
            "firstname": "Tempeste",
            "lastname": "Lagrange",
            "streetaddress": "71 rue Petite Fusterie",
            "city": "BOURG-EN-BRESSE",
            "zipcode": "01000",
            "country": "France",
            "birthdate": "2/5/1997",
            "picture": null
        },
        {
            "GUID": "50a81078-a1fd-4e27-9aad-9fbdcdae9159",
            "gender": "female",
            "firstname": "Fran\u00e7oise",
            "lastname": "Faucher",
            "streetaddress": "69 rue des Chaligny",
            "city": "NICE",
            "zipcode": "06300",
            "country": "France",
            "birthdate": "7/2/1997",
            "picture": null
        },
        {
            "GUID": "a125ab0a-ec1a-4f49-a8ca-c960e3901f6b",
            "gender": "male",
            "firstname": "St\u00e9phane",
            "lastname": "Bourgeois",
            "streetaddress": "4 rue de l'Epeule",
            "city": "ROUEN",
            "zipcode": "76000",
            "country": "France",
            "birthdate": "9/22/1996",
            "picture": null
        },
        {
            "GUID": "45746c1e-d4ff-4889-a597-cb34745a5f5f",
            "gender": "female",
            "firstname": "Amedee",
            "lastname": "Saindon",
            "streetaddress": "32 rue Nationale",
            "city": "PARIS",
            "zipcode": "75003",
            "country": "France",
            "birthdate": "3/18/1996",
            "picture": null
        },
        {
            "GUID": "9d7a8bff-9547-49ce-903f-3ad403952daf",
            "gender": "female",
            "firstname": "Berangaria",
            "lastname": "Proulx",
            "streetaddress": "55 rue Descartes",
            "city": "STRASBOURG",
            "zipcode": "67000",
            "country": "France",
            "birthdate": "8/12/1998",
            "picture": null
        },
        {
            "GUID": "1bbb9471-5e2d-44d4-87ee-ad157c4d9856",
            "gender": "female",
            "firstname": "Margaux",
            "lastname": "Chaloux",
            "streetaddress": "88 place de Miremont",
            "city": "VILLENEUVE-LA-GARENNE",
            "zipcode": "92390",
            "country": "France",
            "birthdate": "1/5/2000",
            "picture": null
        },
        {
            "GUID": "eb1aaddf-568f-492b-a341-18a908ae6e0c",
            "gender": "male",
            "firstname": "Timoth\u00e9e",
            "lastname": "Monty",
            "streetaddress": "84 avenue de Provence",
            "city": "VALENCIENNES",
            "zipcode": "59300",
            "country": "France",
            "birthdate": "2/17/1999",
            "picture": null
        },
        {
            "GUID": "6cb0a37c-e3b9-4bfd-83eb-4da9bce66fa4",
            "gender": "male",
            "firstname": "Francis",
            "lastname": "Laprise",
            "streetaddress": "80 rue Lenotre",
            "city": "RENNES",
            "zipcode": "35000",
            "country": "France",
            "birthdate": "4/5/1999",
            "picture": null
        },
        {
            "GUID": "3df43bd0-d242-4483-b0e4-df362ac9f0dc",
            "gender": "female",
            "firstname": "Azura",
            "lastname": "Beaulac",
            "streetaddress": "25 rue Pierre Motte",
            "city": "SAINT-DIZIER",
            "zipcode": "52100",
            "country": "France",
            "birthdate": "11/5/2000",
            "picture": null
        },
        {
            "GUID": "a0cb463a-2a1e-424c-8d36-09b1dd54e55e",
            "gender": "female",
            "firstname": "Henriette",
            "lastname": "Chastain",
            "streetaddress": "82 rue Ernest Renan",
            "city": "CHELLES",
            "zipcode": "77500",
            "country": "France",
            "birthdate": "10/12/1996",
            "picture": null
        },
        {
            "GUID": "97cb5e29-f9d5-447e-ab7b-0bd5cbe93a18",
            "gender": "female",
            "firstname": "Vedette",
            "lastname": "Thivierge",
            "streetaddress": "35 rue Pierre Motte",
            "city": "SAINT-DIZIER",
            "zipcode": "52100",
            "country": "France",
            "birthdate": "12/19/1999",
            "picture": null
        },
        {
            "GUID": "2224fc2a-9705-477d-869a-ea60554fdfdf",
            "gender": "male",
            "firstname": "Ogier",
            "lastname": "Cr\u00eate",
            "streetaddress": "31 avenue de l'Amandier",
            "city": "BOBIGNY",
            "zipcode": "93000",
            "country": "France",
            "birthdate": "12/21/1998",
            "picture": null
        },
        {
            "GUID": "f6c4221c-463c-4a35-8daf-99927ba59ef7",
            "gender": "female",
            "firstname": "Denise",
            "lastname": "Fug\u00e8re",
            "streetaddress": "68 rue Isambard",
            "city": "FRESNES",
            "zipcode": "94260",
            "country": "France",
            "birthdate": "10/21/1998",
            "picture": null
        },
        {
            "GUID": "d1d2dd33-9caa-400f-ab7f-920130a02d13",
            "gender": "female",
            "firstname": "Esperanza",
            "lastname": "Brousseau",
            "streetaddress": "68 rue de la Mare aux Carats",
            "city": "MONTPELLIER",
            "zipcode": "34080",
            "country": "France",
            "birthdate": "8/5/1996",
            "picture": null
        },
        {
            "GUID": "8ef1e849-1d75-49ca-b9c7-9e201e5411b5",
            "gender": "female",
            "firstname": "Morgana",
            "lastname": "Lamare",
            "streetaddress": "33 Place du Jeu de Paume",
            "city": "VILLEFRANCHE-SUR-SA\u00d4NE",
            "zipcode": "69400",
            "country": "France",
            "birthdate": "11/24/1995",
            "picture": null
        },
        {
            "GUID": "eac9cfbc-9955-4ea0-a5ad-7941f3019fb0",
            "gender": "male",
            "firstname": "Henry",
            "lastname": "Briard",
            "streetaddress": "93 rue du Ch\u00e2teau",
            "city": "SAINT-\u00c9TIENNE",
            "zipcode": "42100",
            "country": "France",
            "birthdate": "7/20/1999",
            "picture": null
        },
        {
            "GUID": "a7e1f4eb-a5b2-4174-a6d9-9d2173afc3f8",
            "gender": "female",
            "firstname": "Yseult",
            "lastname": "Mailloux",
            "streetaddress": "25 rue de la Bo\u00e9tie",
            "city": "POITIERS",
            "zipcode": "86000",
            "country": "France",
            "birthdate": "3/10/1996",
            "picture": null
        },
        {
            "GUID": "a2d2e1e6-8231-41dd-86d7-bf1130971894",
            "gender": "male",
            "firstname": "Nicolas",
            "lastname": "Berie",
            "streetaddress": "82 boulevard Bryas",
            "city": "CROIX",
            "zipcode": "59170",
            "country": "France",
            "birthdate": "2/2/2002",
            "picture": null
        },
        {
            "GUID": "1b584675-c4b1-470f-854b-e3a3ce66d3e5",
            "gender": "male",
            "firstname": "Marc",
            "lastname": "Bordeleau",
            "streetaddress": "51 rue du Clair Bocage",
            "city": "LA VALETTE-DU-VAR",
            "zipcode": "83160",
            "country": "France",
            "birthdate": "5/8/1997",
            "picture": null
        },
        {
            "GUID": "f2c08f63-fea1-4496-b8f4-e96e7b419f8c",
            "gender": "male",
            "firstname": "Maurice",
            "lastname": "Lapresse",
            "streetaddress": "27 rue Petite Fusterie",
            "city": "BOURGOIN-JALLIEU",
            "zipcode": "38300",
            "country": "France",
            "birthdate": "3/20/2000",
            "picture": null
        },
        {
            "GUID": "a8e8c284-a9d6-4623-8289-c14716e87932",
            "gender": "male",
            "firstname": "Thomas",
            "lastname": "Martin",
            "streetaddress": "39 rue Descartes",
            "city": "SURESNES",
            "zipcode": "92150",
            "country": "France",
            "birthdate": "11/30/1994",
            "picture": null
        },
        {
            "GUID": "a69e7e80-0824-43ab-a76f-ad467dfbc9c7",
            "gender": "male",
            "firstname": "Barry",
            "lastname": "Lepage",
            "streetaddress": "51 rue du Clair Bocage",
            "city": "LA VALETTE-DU-VAR",
            "zipcode": "83160",
            "country": "France",
            "birthdate": "8/23/1997",
            "picture": null
        },
        {
            "GUID": "ac49e12e-9e87-434c-8d2b-de1a5b6f3d11",
            "gender": "male",
            "firstname": "Nicholas",
            "lastname": "C\u00f4t\u00e9",
            "streetaddress": "37 rue des Soeurs",
            "city": "JUAN-LES-PINS",
            "zipcode": "06160",
            "country": "France",
            "birthdate": "10/10/1995",
            "picture": null
        },
        {
            "GUID": "67f2b278-322a-497c-a380-45b6571e5203",
            "gender": "male",
            "firstname": "Davet",
            "lastname": "Bordeaux",
            "streetaddress": "56 avenue de l'Amandier",
            "city": "BOBIGNY",
            "zipcode": "93000",
            "country": "France",
            "birthdate": "5/27/1995",
            "picture": null
        },
        {
            "GUID": "09b5222f-5266-4841-8d23-e5461d123b48",
            "gender": "female",
            "firstname": "Anouk",
            "lastname": "Vaillancour",
            "streetaddress": "59 Boulevard de Normandie",
            "city": "FORT-DE-FRANCE",
            "zipcode": "97200",
            "country": "France",
            "birthdate": "3/1/2002",
            "picture": null
        },
        {
            "GUID": "f50ecf17-dd44-4191-a521-3a5cf8a0e062",
            "gender": "female",
            "firstname": "Mavise",
            "lastname": "Dufresne",
            "streetaddress": "19 cours Jean Jaures",
            "city": "BORDEAUX",
            "zipcode": "33200",
            "country": "France",
            "birthdate": "10/4/1998",
            "picture": null
        },
        {
            "GUID": "eea5b586-a075-4e22-83e1-ba875250a956",
            "gender": "male",
            "firstname": "Christian",
            "lastname": "Jolicoeur",
            "streetaddress": "69 cours Jean Jaures",
            "city": "BORDEAUX",
            "zipcode": "33800",
            "country": "France",
            "birthdate": "5/18/1996",
            "picture": null
        },
        {
            "GUID": "33ddaee5-d09c-4b5e-b6c9-bdd0280bf037",
            "gender": "male",
            "firstname": "Jacques",
            "lastname": "Bouvier",
            "streetaddress": "90 Chemin Challet",
            "city": "LI\u00c9VIN",
            "zipcode": "62800",
            "country": "France",
            "birthdate": "6/3/1995",
            "picture": null
        },
        {
            "GUID": "9b1068be-7dbc-4eeb-9a84-a78112b4588a",
            "gender": "male",
            "firstname": "Orville",
            "lastname": "Bois",
            "streetaddress": "16 Place de la Madeleine",
            "city": "PARIS",
            "zipcode": "75009",
            "country": "France",
            "birthdate": "6/13/1995",
            "picture": null
        },
        {
            "GUID": "f56b02ec-b3ef-4379-9606-358170a20659",
            "gender": "male",
            "firstname": "Marsilius",
            "lastname": "DuLin",
            "streetaddress": "81 Rue Bonnet",
            "city": "VOIRON",
            "zipcode": "38500",
            "country": "France",
            "birthdate": "5/31/1997",
            "picture": null
        },
        {
            "GUID": "3fdae159-c5bb-4925-bfc4-a4f5f21f83a5",
            "gender": "female",
            "firstname": "Rosamonde",
            "lastname": "Jolicoeur",
            "streetaddress": "87 Place du Jeu de Paume",
            "city": "VILLEFRANCHE-SUR-SA\u00d4NE",
            "zipcode": "69400",
            "country": "France",
            "birthdate": "7/12/2001",
            "picture": null
        },
        {
            "GUID": "cfd1f704-fe74-470e-9c24-8fa619f5681f",
            "gender": "male",
            "firstname": "Onfroi",
            "lastname": "Drouin",
            "streetaddress": "98 rue Porte d'Orange",
            "city": "CAVAILLON",
            "zipcode": "84300",
            "country": "France",
            "birthdate": "4/16/2000",
            "picture": null
        },
        {
            "GUID": "ec29aca5-9268-437a-be07-97413e90c263",
            "gender": "female",
            "firstname": "Allyriane",
            "lastname": "Lesage",
            "streetaddress": "24 Rue Marie De M\u00e9dicis",
            "city": "CARCASSONNE",
            "zipcode": "11000",
            "country": "France",
            "birthdate": "6/24/1998",
            "picture": null
        },
        {
            "GUID": "17a3cfcf-cf24-4798-9f2d-5cd357423616",
            "gender": "female",
            "firstname": "Henriette",
            "lastname": "Barrientos",
            "streetaddress": "81 Rue Bonnet",
            "city": "YERRES",
            "zipcode": "91330",
            "country": "France",
            "birthdate": "1/7/1999",
            "picture": null
        },
        {
            "GUID": "83fcf8ca-de89-4ea1-917c-ff4df8c0235a",
            "gender": "male",
            "firstname": "Tyson",
            "lastname": "Gaillard",
            "streetaddress": "99 rue Bonneterie",
            "city": "MIRAMAS",
            "zipcode": "13140",
            "country": "France",
            "birthdate": "3/14/1999",
            "picture": null
        },
        {
            "GUID": "751479ef-3ef2-48fe-9237-c37ae6454c18",
            "gender": "male",
            "firstname": "Gustave",
            "lastname": "Lang",
            "streetaddress": "26 Rue St Ferr\u00e9ol",
            "city": "MEUDON",
            "zipcode": "92190",
            "country": "France",
            "birthdate": "4/14/1997",
            "picture": null
        },
        {
            "GUID": "9b3be251-5517-42dc-bfab-fbb91562df8d",
            "gender": "female",
            "firstname": "Odette",
            "lastname": "Leroux",
            "streetaddress": "47 rue Grande Fusterie",
            "city": "BRON",
            "zipcode": "69500",
            "country": "France",
            "birthdate": "7/18/2000",
            "picture": null
        },
        {
            "GUID": "49291405-9376-4e5e-a81f-dfd67c994a75",
            "gender": "male",
            "firstname": "Merlin",
            "lastname": "Rochefort",
            "streetaddress": "16 quai Saint-Nicolas",
            "city": "TOURS",
            "zipcode": "37100",
            "country": "France",
            "birthdate": "7/22/2001",
            "picture": null
        },
        {
            "GUID": "6ab97ed8-8808-4dd6-8808-1d23d91a909c",
            "gender": "female",
            "firstname": "Melodie",
            "lastname": "Saucier",
            "streetaddress": "26 rue Sadi Carnot",
            "city": "AURILLAC",
            "zipcode": "15000",
            "country": "France",
            "birthdate": "6/17/1995",
            "picture": null
        },
        {
            "GUID": "8236dad7-9001-4225-9928-ca04552b5dd3",
            "gender": "male",
            "firstname": "Germain",
            "lastname": "\u00c9toile",
            "streetaddress": "44 rue des six fr\u00e8res Ruellan",
            "city": "SALON-DE-PROVENCE",
            "zipcode": "13300",
            "country": "France",
            "birthdate": "8/11/1996",
            "picture": null
        },
        {
            "GUID": "31fa2245-29f3-44f9-9cd3-ff6f056fff34",
            "gender": "female",
            "firstname": "Arnaude",
            "lastname": "Varieur",
            "streetaddress": "43 rue de Groussay",
            "city": "ROSNY-SOUS-BOIS",
            "zipcode": "93110",
            "country": "France",
            "birthdate": "5/20/1995",
            "picture": null
        },
        {
            "GUID": "ce2f4109-0659-4125-b64a-2f1ba929b276",
            "gender": "female",
            "firstname": "Rosamonde",
            "lastname": "Devoe",
            "streetaddress": "20 rue Marie de M\u00e9dicis",
            "city": "B\u00c9ZIERS",
            "zipcode": "34500",
            "country": "France",
            "birthdate": "3/2/2000",
            "picture": null
        },
        {
            "GUID": "def77e06-6047-459f-b880-6972ae303bcd",
            "gender": "male",
            "firstname": "Courtland",
            "lastname": "Lemieux",
            "streetaddress": "4 Rue du Palais",
            "city": "\u00c9PERNAY",
            "zipcode": "51200",
            "country": "France",
            "birthdate": "3/15/1997",
            "picture": null
        },
        {
            "GUID": "1729a355-c862-4d70-aec2-3b99abcc333c",
            "gender": "female",
            "firstname": "Xavierre",
            "lastname": "Hupp\u00e9",
            "streetaddress": "28 rue du Clair Bocage",
            "city": "LA VALETTE-DU-VAR",
            "zipcode": "83160",
            "country": "France",
            "birthdate": "7/30/1999",
            "picture": null
        },
        {
            "GUID": "595f24d7-22c5-4c48-9dae-382b8816f3f1",
            "gender": "male",
            "firstname": "Nicolas",
            "lastname": "Vernadeau",
            "streetaddress": "63 rue Cazade",
            "city": "DRANCY",
            "zipcode": "93700",
            "country": "France",
            "birthdate": "7/12/2000",
            "picture": null
        },
        {
            "GUID": "c9c4812f-9c3f-4a12-a2f0-907bd7248821",
            "gender": "female",
            "firstname": "Claudette",
            "lastname": "Corbin",
            "streetaddress": "25 avenue de Provence",
            "city": "VALENCIENNES",
            "zipcode": "59300",
            "country": "France",
            "birthdate": "2/16/2000",
            "picture": null
        },
        {
            "GUID": "e0bc0cc6-36e7-48a5-bba4-b2e09c0102b2",
            "gender": "female",
            "firstname": "Albracca",
            "lastname": "Vertefeuille",
            "streetaddress": "61 rue Pierre Motte",
            "city": "SAINT-DIZIER",
            "zipcode": "52100",
            "country": "France",
            "birthdate": "4/2/2000",
            "picture": null
        },
        {
            "GUID": "a151e938-1622-4392-8f11-712388de929a",
            "gender": "male",
            "firstname": "Javier",
            "lastname": "de Launay",
            "streetaddress": "46 Avenue des Pr'es",
            "city": "MONTMORENCY",
            "zipcode": "95160",
            "country": "France",
            "birthdate": "9/16/1995",
            "picture": null
        },
        {
            "GUID": "55f010eb-c530-4cab-a7da-257f050dc5e3",
            "gender": "male",
            "firstname": "Marc",
            "lastname": "Laforest",
            "streetaddress": "37 cours Jean Jaures",
            "city": "BORDEAUX",
            "zipcode": "33200",
            "country": "France",
            "birthdate": "7/10/1995",
            "picture": null
        },
        {
            "GUID": "b6d335ab-8930-4a84-b188-b8b5f5b5cb24",
            "gender": "female",
            "firstname": "Leone",
            "lastname": "Marchesseault",
            "streetaddress": "18 Boulevard de Normandie",
            "city": "FORBACH",
            "zipcode": "57600",
            "country": "France",
            "birthdate": "1/15/2001",
            "picture": null
        },
        {
            "GUID": "ec7ab68a-3d9f-40f7-890c-3e5d566faae1",
            "gender": "male",
            "firstname": "Joseph",
            "lastname": "Jolicoeur",
            "streetaddress": "93 Place Napol\u00e9on",
            "city": "LE BLANC-MESNIL",
            "zipcode": "93150",
            "country": "France",
            "birthdate": "1/20/1996",
            "picture": null
        },
        {
            "GUID": "e85d0b0f-0704-49f6-ab76-f8c66424341c",
            "gender": "male",
            "firstname": "Agramant",
            "lastname": "Thibault",
            "streetaddress": "89 rue Sadi Carnot",
            "city": "AULNAY-SOUS-BOIS",
            "zipcode": "93600",
            "country": "France",
            "birthdate": "1/27/2000",
            "picture": null
        },
        {
            "GUID": "41d75d53-1226-439c-93a1-bfb0ebba51a9",
            "gender": "male",
            "firstname": "Leverett",
            "lastname": "Bonenfant",
            "streetaddress": "27 rue S\u00e9bastopol",
            "city": "SAINTES",
            "zipcode": "17100",
            "country": "France",
            "birthdate": "3/24/2000",
            "picture": null
        },
        {
            "GUID": "69a0ff68-c99f-4a5e-b7fe-12c3a9ca0446",
            "gender": "female",
            "firstname": "Cendrillon",
            "lastname": "Josseaume",
            "streetaddress": "88 boulevard Amiral Courbet",
            "city": "OYONNAX",
            "zipcode": "01100",
            "country": "France",
            "birthdate": "5/13/2002",
            "picture": null
        },
        {
            "GUID": "7e7842cd-45f4-4298-b237-96041f0b958d",
            "gender": "female",
            "firstname": "Maurelle",
            "lastname": "Chartier",
            "streetaddress": "12 Rue du Limas",
            "city": "BASTIA",
            "zipcode": "20200",
            "country": "France",
            "birthdate": "2/20/1995",
            "picture": null
        },
        {
            "GUID": "5455e6a4-3ab0-4f7c-8d0c-2ed91503c071",
            "gender": "male",
            "firstname": "Parfait",
            "lastname": "Fug\u00e8re",
            "streetaddress": "25 rue Banaudon",
            "city": "LYON",
            "zipcode": "69008",
            "country": "France",
            "birthdate": "3/4/1997",
            "picture": null
        },
        {
            "GUID": "5568a897-cd7b-4768-ada7-e3408ac46ee9",
            "gender": "female",
            "firstname": "Anouk",
            "lastname": "Guimond",
            "streetaddress": "89 rue du Gue Jacquet",
            "city": "CHATOU",
            "zipcode": "78400",
            "country": "France",
            "birthdate": "7/10/1997",
            "picture": null
        },
        {
            "GUID": "4b0bfa73-e820-4921-b5e5-a9b3ab230794",
            "gender": "female",
            "firstname": "Genevre",
            "lastname": "Brodeur",
            "streetaddress": "93 avenue Ferdinand de Lesseps",
            "city": "GRANDE-SYNTHE",
            "zipcode": "59760",
            "country": "France",
            "birthdate": "8/24/2002",
            "picture": null
        },
        {
            "GUID": "aec68a37-2259-4e0b-99e9-5ee5f5222a35",
            "gender": "male",
            "firstname": "Mayhew",
            "lastname": "Croteau",
            "streetaddress": "86 rue Victor Hugo",
            "city": "CONCARNEAU",
            "zipcode": "29900",
            "country": "France",
            "birthdate": "11/25/2001",
            "picture": null
        },
        {
            "GUID": "f3321221-5d5b-4ed6-a21a-7bec253e7536",
            "gender": "male",
            "firstname": "Iven",
            "lastname": "Ducharme",
            "streetaddress": "69 rue du Faubourg National",
            "city": "THIAIS",
            "zipcode": "94320",
            "country": "France",
            "birthdate": "8/11/1997",
            "picture": null
        },
        {
            "GUID": "802c9a76-f77f-49dd-b4f5-f58dd4aab991",
            "gender": "female",
            "firstname": "Val\u00e9rie",
            "lastname": "Guernon",
            "streetaddress": "5 rue Grande Fusterie",
            "city": "BRIVE-LA-GAILLARDE",
            "zipcode": "19100",
            "country": "France",
            "birthdate": "8/10/1996",
            "picture": null
        },
        {
            "GUID": "a6f3a1ce-b717-4643-a25f-e2990a10b8a9",
            "gender": "female",
            "firstname": "Diane",
            "lastname": "Sabourin",
            "streetaddress": "27 Place Napol\u00e9on",
            "city": "LE BLANC-MESNIL",
            "zipcode": "93150",
            "country": "France",
            "birthdate": "11/11/1994",
            "picture": null
        },
        {
            "GUID": "8642e989-5424-411d-a595-41f4e266a5f1",
            "gender": "female",
            "firstname": "Faye",
            "lastname": "Quenneville",
            "streetaddress": "19 rue du Gue Jacquet",
            "city": "CH\u00c2TENAY-MALABRY",
            "zipcode": "92290",
            "country": "France",
            "birthdate": "3/25/1997",
            "picture": null
        },
        {
            "GUID": "c166ad2b-fd2b-4bca-9389-0e93fb6b48f6",
            "gender": "female",
            "firstname": "Alice",
            "lastname": "Caron",
            "streetaddress": "57 rue du Pr\u00e9sident Roosevelt",
            "city": "SCHILTIGHEIM",
            "zipcode": "67300",
            "country": "France",
            "birthdate": "8/11/2000",
            "picture": null
        },
        {
            "GUID": "c0388f76-22b9-4769-a2d4-e70c5377556d",
            "gender": "male",
            "firstname": "Mayhew",
            "lastname": "Auclair",
            "streetaddress": "16 route de Lyon",
            "city": "ILLKIRCH-GRAFFENSTADEN",
            "zipcode": "67400",
            "country": "France",
            "birthdate": "2/28/2001",
            "picture": null
        },
        {
            "GUID": "6956cd25-d2fd-4efc-b689-09a99c43d218",
            "gender": "male",
            "firstname": "Joseph",
            "lastname": "Robitaille",
            "streetaddress": "99 place de Miremont",
            "city": "VILLENEUVE-SAINT-GEORGES",
            "zipcode": "94190",
            "country": "France",
            "birthdate": "4/21/2001",
            "picture": null
        },
        {
            "GUID": "8794dd34-a4cf-4aa5-8487-30ad2288d69c",
            "gender": "female",
            "firstname": "Robinette",
            "lastname": "Chartier",
            "streetaddress": "79 avenue Jean Portalis",
            "city": "TULLE",
            "zipcode": "19000",
            "country": "France",
            "birthdate": "2/20/1998",
            "picture": null
        },
        {
            "GUID": "6d060975-c0ee-4d30-964f-287dc6d463d2",
            "gender": "male",
            "firstname": "Warrane",
            "lastname": "Varieur",
            "streetaddress": "70 rue Adolphe Wurtz",
            "city": "LE PLESSIS-ROBINSON",
            "zipcode": "92350",
            "country": "France",
            "birthdate": "7/27/2002",
            "picture": null
        },
        {
            "GUID": "57e5fc41-3602-4b3e-bca0-1e64773ba9cd",
            "gender": "male",
            "firstname": "Donat",
            "lastname": "Dup\u00e9r\u00e9",
            "streetaddress": "59 rue Michel Ange",
            "city": "LE KREMLIN-BIC\u00caTRE",
            "zipcode": "94270",
            "country": "France",
            "birthdate": "9/19/1999",
            "picture": null
        },
        {
            "GUID": "a06e38ad-0894-4fbf-b7e3-0aeb7af045a0",
            "gender": "female",
            "firstname": "Tempeste",
            "lastname": "Robert",
            "streetaddress": "71 rue de Geneve",
            "city": "AMIENS",
            "zipcode": "80080",
            "country": "France",
            "birthdate": "3/1/2002",
            "picture": null
        },
        {
            "GUID": "ea249fd8-bf0f-45cc-8f2f-ac969e1356b9",
            "gender": "male",
            "firstname": "Ogier",
            "lastname": "Goudreau",
            "streetaddress": "93 avenue Voltaire",
            "city": "M\u00c2CON",
            "zipcode": "71000",
            "country": "France",
            "birthdate": "6/30/1995",
            "picture": null
        },
        {
            "GUID": "8fb3892d-545a-4403-887f-6600aff7d6f0",
            "gender": "female",
            "firstname": "Coralie",
            "lastname": "Pinneau",
            "streetaddress": "92 Avenue des Pr'es",
            "city": "MONTLU\u00c7ON",
            "zipcode": "03100",
            "country": "France",
            "birthdate": "2/15/2001",
            "picture": null
        },
        {
            "GUID": "c14f818c-7418-46a7-92d4-2002d1be9e48",
            "gender": "female",
            "firstname": "Julienne",
            "lastname": "Abril",
            "streetaddress": "79 Place du Jeu de Paume",
            "city": "VILLEFRANCHE-SUR-SA\u00d4NE",
            "zipcode": "69400",
            "country": "France",
            "birthdate": "7/1/2000",
            "picture": null
        },
        {
            "GUID": "7ee926f1-f53f-4e98-ba2d-41201f2dbbba",
            "gender": "male",
            "firstname": "Gustave",
            "lastname": "Lagrange",
            "streetaddress": "55 Place de la Madeleine",
            "city": "PARIS",
            "zipcode": "75012",
            "country": "France",
            "birthdate": "5/14/2001",
            "picture": null
        },
        {
            "GUID": "6c13481a-86de-4052-a7f3-d01ef07b8581",
            "gender": "female",
            "firstname": "Aim\u00e9e",
            "lastname": "Duplanty",
            "streetaddress": "97 Rue Roussy",
            "city": "NOUM\u00c9A",
            "zipcode": "98800",
            "country": "France",
            "birthdate": "3/11/1997",
            "picture": null
        },
        {
            "GUID": "0283f12b-5ffe-4428-bd09-2f55995b6f79",
            "gender": "female",
            "firstname": "Cendrillon",
            "lastname": "Gladu",
            "streetaddress": "78 rue Cazade",
            "city": "DUNKERQUE",
            "zipcode": "59240",
            "country": "France",
            "birthdate": "8/29/1997",
            "picture": null
        },
        {
            "GUID": "1efd1605-5548-4c50-b497-7c99b2cff4b1",
            "gender": "male",
            "firstname": "Peverell",
            "lastname": "Du Trieux",
            "streetaddress": "5 Rue Joseph Vernet",
            "city": "BAGNOLET",
            "zipcode": "93170",
            "country": "France",
            "birthdate": "1/11/1997",
            "picture": null
        },
        {
            "GUID": "1e4a6ef6-73c2-442e-95b2-595e6a7aa114",
            "gender": "female",
            "firstname": "Roux",
            "lastname": "Pellerin",
            "streetaddress": "36 rue de la Mare aux Carats",
            "city": "MONTREUIL",
            "zipcode": "93100",
            "country": "France",
            "birthdate": "3/10/1998",
            "picture": null
        },
        {
            "GUID": "60e3a89f-0c7e-49e1-85e2-727866159482",
            "gender": "female",
            "firstname": "Noelle",
            "lastname": "Montminy",
            "streetaddress": "20 Place Napol\u00e9on",
            "city": "LAMBERSART",
            "zipcode": "59130",
            "country": "France",
            "birthdate": "12/11/1994",
            "picture": null
        },
        {
            "GUID": "8a68ce07-3872-4bea-9492-36c72bd30662",
            "gender": "female",
            "firstname": "Zara",
            "lastname": "Auclair",
            "streetaddress": "9 Avenue des Tuileries",
            "city": "HAZEBROUCK",
            "zipcode": "59190",
            "country": "France",
            "birthdate": "8/28/1995",
            "picture": null
        },
        {
            "GUID": "1388193d-0ba3-41fb-b0ef-ecfdbab68038",
            "gender": "male",
            "firstname": "Ray",
            "lastname": "Beauchemin",
            "streetaddress": "85 rue de Geneve",
            "city": "ALFORTVILLE",
            "zipcode": "94140",
            "country": "France",
            "birthdate": "10/28/1999",
            "picture": null
        },
        {
            "GUID": "8cf949ba-c068-4811-9faa-554586b7774f",
            "gender": "female",
            "firstname": "Lucille",
            "lastname": "Coupart",
            "streetaddress": "49 rue Banaudon",
            "city": "LYON",
            "zipcode": "69008",
            "country": "France",
            "birthdate": "10/17/1995",
            "picture": null
        },
        {
            "GUID": "7e1bac59-6812-4c86-aa58-fe573727d87f",
            "gender": "male",
            "firstname": "Aubrey",
            "lastname": "DuLin",
            "streetaddress": "13 rue Cazade",
            "city": "DRANCY",
            "zipcode": "93700",
            "country": "France",
            "birthdate": "4/20/1995",
            "picture": null
        },
        {
            "GUID": "fb67881c-9b84-4e63-a342-a00a033c8c3f",
            "gender": "male",
            "firstname": "Ansel",
            "lastname": "Quirion",
            "streetaddress": "39 avenue de Provence",
            "city": "VANDOEUVRE-L\u00c8S-NANCY",
            "zipcode": "54500",
            "country": "France",
            "birthdate": "10/14/1996",
            "picture": null
        },
        {
            "GUID": "a4b0faf5-399a-4333-a132-22b805a22fce",
            "gender": "male",
            "firstname": "Frontino",
            "lastname": "Brian",
            "streetaddress": "21 rue Marie de M\u00e9dicis",
            "city": "B\u00c9THUNE",
            "zipcode": "62400",
            "country": "France",
            "birthdate": "10/5/1997",
            "picture": null
        },
        {
            "GUID": "c72a3a88-797f-41bf-a9d4-06bfbbe9ab63",
            "gender": "male",
            "firstname": "Brice",
            "lastname": "Thivierge",
            "streetaddress": "34 avenue de Provence",
            "city": "VALLAURIS",
            "zipcode": "06220",
            "country": "France",
            "birthdate": "10/30/1996",
            "picture": null
        },
        {
            "GUID": "da740a9c-899c-4c59-84e1-27be0a089c6d",
            "gender": "female",
            "firstname": "Vivienne",
            "lastname": "Fresne",
            "streetaddress": "32 rue Descartes",
            "city": "SURESNES",
            "zipcode": "92150",
            "country": "France",
            "birthdate": "10/17/1999",
            "picture": null
        },
        {
            "GUID": "d6ae9059-1a8c-4892-8cc1-71edf0361197",
            "gender": "female",
            "firstname": "C\u00e9line",
            "lastname": "Vaillancour",
            "streetaddress": "1 rue Charles Corbeau",
            "city": "F\u00c9CAMP",
            "zipcode": "76400",
            "country": "France",
            "birthdate": "8/20/2002",
            "picture": null
        },
        {
            "GUID": "aebf6c2f-847c-4cd0-9d0f-95309ed9f21d",
            "gender": "female",
            "firstname": "Cendrillon",
            "lastname": "L\u00e9veill\u00e9",
            "streetaddress": "74 Rue Joseph Vernet",
            "city": "AVIGNON",
            "zipcode": "84000",
            "country": "France",
            "birthdate": "8/31/2001",
            "picture": null
        },
        {
            "GUID": "d45c3e5c-a70e-4bf3-8b88-e9f70e3f01e4",
            "gender": "male",
            "firstname": "Benjamin",
            "lastname": "Faure",
            "streetaddress": "60 rue Bonneterie",
            "city": "MONS-EN-BAROEUL",
            "zipcode": "59370",
            "country": "France",
            "birthdate": "11/28/2000",
            "picture": null
        },
        {
            "GUID": "98379e40-c8d1-45e9-8c1c-5e3b6985b6e6",
            "gender": "male",
            "firstname": "Xarles",
            "lastname": "Mailhot",
            "streetaddress": "61 rue du Faubourg National",
            "city": "TAVERNY",
            "zipcode": "95150",
            "country": "France",
            "birthdate": "8/7/2002",
            "picture": null
        },
        {
            "GUID": "bba06c82-5379-4487-bd90-26b309c146f1",
            "gender": "male",
            "firstname": "Bartlett",
            "lastname": "Neufville",
            "streetaddress": "24 rue des Soeurs",
            "city": "LA COURNEUVE",
            "zipcode": "93120",
            "country": "France",
            "birthdate": "4/7/2000",
            "picture": null
        }
    ]
}